zen/__init__.py
zen/cli/__init__.py
zen/cli/main.py
zen/core/__init__.py
zen/core/exceptions.py
zen/core/installer.py
zen/core/logger.py
zen/schemas/__init__.py
zen/schemas/component.py
zen/schemas/registry.py
zen_unstable-0.1.0.dist-info/METADATA
zen_unstable-0.1.0.dist-info/WHEEL
zen_unstable-0.1.0.dist-info/entry_points.txt
zen_unstable-0.1.0.dist-info/top_level.txt
zen_unstable-0.1.0.dist-info/RECORD
