Metadata-Version: 2.4
Name: zen-unstable
Version: 0.1.0
Summary: Python component registry system - like shadcn/ui for Python
Author: TheRaj71
Author-email: theraj71@example.com
Keywords: components,registry,shadcn,python,cli,zen
Classifier: Development Status :: 4 - Beta
Classifier: Intended Audience :: Developers
Classifier: License :: OSI Approved :: MIT License
Classifier: Operating System :: OS Independent
Classifier: Programming Language :: Python :: 3
Classifier: Programming Language :: Python :: 3.8
Classifier: Programming Language :: Python :: 3.9
Classifier: Programming Language :: Python :: 3.10
Classifier: Programming Language :: Python :: 3.11
Classifier: Programming Language :: Python :: 3.12
Classifier: Topic :: Software Development :: Libraries :: Python Modules
Classifier: Topic :: Software Development :: Code Generators
Classifier: Topic :: System :: Software Distribution
Requires-Python: >=3.8
Dynamic: author
Dynamic: author-email
Dynamic: classifier
Dynamic: description
Dynamic: description-content-type
Dynamic: keywords
Dynamic: requires-python
Dynamic: summary
